{
  "eui.CANCEL": "Annullér",
  "eui.EXPANDALL": "Vis alle",
  "eui.COLLAPSEALL": "Skjul alle",
  "eui.FILTER": "Filtrér",
  "eui.TODAY": "i dag",
  "eui.ONEDAYAGO": "for en dag siden",
  "eui.INONEDAY": "om en dag",
  "eui.XDAYSAGO ": "{{days}} dage siden",
  "eui.INXDAYS": "om {{days}} dage",
  "eui.YES": "Ja",
  "eui.NO": "Nej",
  "eui.OK": "Ok",
  "eui.REFRESH": "Opdatér",
  "eui.SETTINGS": "Indstillinger",
  "eui.VIEWALLNOTIFICATIONS": "Se alle notifikationer",
  "eui.MYNOTIFICATIONS": "Mine notifikationer",
  "eui.NONOTIFICATIONFOUND": "Der blev ikke fundet nogen notifikation",
  "eui.NOTIFICATIONMARKASREAD": "Markér som læst",
  "eui.NOTIFICATIONMARKASUNREAD": "Markér som ulæst",
  "eui.NOTIFICATIONMARKALLASREAD": "Markér alle som læst",
  "eui.NOTIFICATIONSTODAY": "Dagens notifikationer",
  "eui.NOTIFICATIONSOLDEST": "Ældste notifikationer",
  "eui.NOTIFICATIONSUNREAD": "Ulæste",
  "eui.NOTIFICATIONSTOTAL": "I alt",
  "eui.AUTOCOMPLETETAGREQUIREDITEMSREQUIRED": "Du skal vælge et punkt",
  "eui.AUTOCOMPLETETAGREQUIREDITEMSVALIDATION": "Du skal vælge yderligere {{items}} punkt(er) på listen",
  "eui.AUTOCOMPLETETAGMAXREQUIREDITEMSVALIDATION": "Maks. antal elementer overskredet (maks.: {{maximum}} / valgt: {{actual}})",
  "eui.FILTERS": "Filtre",
  "eui.ADVANCEDFILTER": "Avanceret filter",
  "eui.ADVANCEDSEARCH": "Avanceret søgning",
  "eui.NAVIGATION": "Navigering",
  "eui.QUICKFILTER": "Kvikfilter",
  "eui.SEARCH": "Søg",
  "eui.RESULTS": "Resultater",
  "eui.PLACEHOLDERSEARCH": "Søg...",
  "eui.LAYOUTPAGEHEADER.ADDTOFAVOURITES": "Tilføj til favoritter",
  "eui.LAYOUTPAGEHEADER.EDITFAVOURITES": "Redigér favoritter",
  "eui.LAYOUTPAGEHEADER.FAVOURITES": "Favoritter",
  "eui.LAYOUTPAGEHEADER.PRINT": "Udskriv",
  "eui.LAYOUTPAGEHEADER.EXPORT": "Eksportér",
  "eui.LAYOUTPAGEHEADER.SHARE": "Del",
  "eui.LAYOUTPAGEHEADER.HELP": "Hjælp",
  "eui.CONNECTED": "Du er logget ind",
  "eui.NOTCONNECTED": "Du er ikke logget ind",
  "eui.dashboard.DASHBOARD": "Dashboard",
  "eui.dashboard.DASHBOARD-NAME": "Dashboard-navn",
  "eui.dashboard.SELECTED-DASHBOARD": "valgt dashboard",
  "eui.dashboard.CONFIGURE-YOUR-DASHBOARD": "Konfigurér dit dashboard",
  "eui.dashboard.CANCEL": "Annullér",
  "eui.dashboard.NEXT": "Næste",
  "eui.dashboard.DELETE": "Slet",
  "eui.dashboard.CREATE-NEW-DASHBOARD": "Opret nyt dashboard",
  "eui.dashboard.MY-DASHBOARD-NAME": "Mit dashboard-navn",
  "eui.dashboard.DASHBOARD-NAME-MANDATORY": "Dashboard-navn skal angives",
  "eui.dashboard.DASHBOARD-NAME-TOO-SHORT": "Dette dashboard-navn er for kort",
  "eui.dashboard.DASHBOARD-NAME-TOO-LONG": "Dette dashboard-navn er for langt",
  "eui.dashboard.DASHBOARD-NAME-ALREADY-EXISTS": "Dette dashboard-navn findes allerede",
  "eui.dashboard.COPY-FROM-CURRENT-DASHBOARD": "Kopiér fra det nuværende dashboard",
  "eui.dashboard.CREATE-FROM-A-BLANK-DASHBOARD": "Opret fra et tomt dashboard",
  "eui.dashboard.RENAME": "Omdøb",
  "eui.dashboard.SAVE": "Gem",
  "eui.dashboard.RETRY": "Prøv igen",
  "eui.dashboard.PREVIOUS": "Foregående",
  "eui.dashboard.ERROR": "Fejl",
  "eui.dashboard.NO-WIDGETS-IN-DASHBOARD": "Du har endnu ikke nogen widget konfigureret til dette dashboard. Brug knappen <strong>tilpas</strong> til at tilføje nye widgets...",
  "eui.dashboard.YOU-ARE-CURRENTLY-ON": "Du befinder dig nu på <strong>{{ value }} dashboard</strong>",
  "eui.dashboard.THE-DEFAULT-DASHBOARD-CANNOT-BE-MODIFIED": "<span class=\"ux-u-color-warning-darkest\"><strong>Standard-</strong>dashboardet kan ikke ændres! </span> Opret et nyt dashboard for at konfigurere dine widgets.",
  "eui.dashboard.AVAILABLE-WIDGETS": "Tilgængelige widgets",
  "eui.dashboard.PLEASE-SELECT-THE-WIDGETS": "Vælg de widgets, du vil vise på dit dashboard.",
  "eui.dashboard.CUSTOMIZE": "Tilpas",
  "eui.dashboard.CLOSE-CUSTOMIZE": "Luk tilpasningsfunktionen",
  "eui.datepicker.PLACEHOLDER": "dd/mm/åååå",
  "eui.datepicker.YEAR-PLACEHOLDER": "åååå",
  "eui.datepicker.MONTH-PLACEHOLDER": "mm/åååå",
  "eui.datepicker.ISDATETIMEPICKER": "dd/mm/åååå tt:mm",
  "eui.SHOW-MORE": "Vis mere",
  "eui.SHOW-LESS": "Vis mindre",
  "eui.daterangeselector.FIRSTPICKERSLABEL": "Startdato",
  "eui.daterangeselector.SECONDPICKERSLABEL": "Slutdato",
  "eui.daterangeselector.FIRSTPICKERSPLACEHOLDER": "dd/mm/åååå",
  "eui.daterangeselector.SECONDPICKERSPLACEHOLDER": "dd/mm/åååå",
  "eui.errorManager.nonGroupText": "Ikke-grupperede fejl",
  "eui.errorManager.followText": "Klik for at følge linket til dette element",
  "eui.pageHeader.ADD-BOOKMARK": "Gem som bogmærke",
  "eui.pageHeader.ADD-BOOKMARK-TOOLTIP": "Tilføj et bogmærke til denne side",
  "eui.pageHeader.REMOVE-BOOKMARK": "Fjern bogmærke",
  "eui.pageHeader.REMOVE-BOOKMARK-TOOLTIP": "Fjern bogmærke til denne side",
  "eui.euitable.ITEMS-PER-PAGE": "Antal resultater pr. side",
  "eui.euitable.RANGE-LABEL": "af",
  "eui.euitable.SHOWING-RANGE": "Viser {{ range }}",
  "eui.fileUpload.chooseFiles": "Vælg filer",
  "eui.fileUpload.chooseFile": "Vælg fil",
  "eui.fileUpload.dragAndDrop": "Bare træk og slip filer her",
  "eui.fileUpload.maxNumberOfFilesExceed.summary": "Maksimalt antal valgte filer overskredet",
  "eui.fileUpload.maxNumberOfFilesExceed.details": "Vælg {{ numberOfFiles }} filer",
  "eui.fileUpload.uploadFile": "Upload fil",
  "eui.fileUpload.removeFile": "Fjern fil",
  "eui.fileUpload.uploadAll": "Upload alle",
  "eui.euifileupload.DRAG-AND-DROP-FILE-HERE": "Træk og slip filen her",
  "eui.euifileupload.CHOOSE-FILE": "Vælg fil",
  "eui.euifileupload.RESET-LIST": "Nulstil liste",
  "eui.euifileupload.TOTAL-SIZE": "samlet størrelse",
  "eui.uxtree.SELECT-ALL": "Vælg alle",
  "eui.uxtree.UNSELECT-ALL": "Fravælg alle",
  "eui.languageSelector.modalTitle": "Vælg sprog"
}